odoo/addons/account_invoice_crm_tag/README.rst
odoo/addons/account_invoice_crm_tag/__init__.py
odoo/addons/account_invoice_crm_tag/__manifest__.py
odoo/addons/account_invoice_crm_tag/i18n/account_invoice_crm_tag.pot
odoo/addons/account_invoice_crm_tag/i18n/es.po
odoo/addons/account_invoice_crm_tag/i18n/it.po
odoo/addons/account_invoice_crm_tag/models/__init__.py
odoo/addons/account_invoice_crm_tag/models/account_move.py
odoo/addons/account_invoice_crm_tag/models/sale_order.py
odoo/addons/account_invoice_crm_tag/readme/CONTRIBUTORS.md
odoo/addons/account_invoice_crm_tag/readme/DESCRIPTION.md
odoo/addons/account_invoice_crm_tag/readme/USAGE.md
odoo/addons/account_invoice_crm_tag/report/__init__.py
odoo/addons/account_invoice_crm_tag/report/account_invoice_report.py
odoo/addons/account_invoice_crm_tag/report/account_invoice_report.xml
odoo/addons/account_invoice_crm_tag/static/description/icon.png
odoo/addons/account_invoice_crm_tag/static/description/index.html
odoo/addons/account_invoice_crm_tag/views/account_invoice_views.xml
odoo_addon_account_invoice_crm_tag-18.0.1.0.0.2.dist-info/METADATA
odoo_addon_account_invoice_crm_tag-18.0.1.0.0.2.dist-info/WHEEL
odoo_addon_account_invoice_crm_tag-18.0.1.0.0.2.dist-info/top_level.txt
odoo_addon_account_invoice_crm_tag-18.0.1.0.0.2.dist-info/RECORD
